MANIFEST.in
README.markdown
gravatar.py
setup.py
pyGravatar.egg-info/PKG-INFO
pyGravatar.egg-info/SOURCES.txt
pyGravatar.egg-info/dependency_links.txt
pyGravatar.egg-info/top_level.txt