Metadata-Version: 1.0
Name: pyGravatar
Version: 0.0.5
Summary: Python module for interacting with Gravatar
Home-page: http://bitbucket.org/gridaphobe/pygravatar
Author: Eric Seidel
Author-email: gridaphobe@gmail.com
License: GPL
Keywords: gravatar
Platform: UNKNOWN
